hwp_metadata_mcp/__init__.py
hwp_metadata_mcp/hml_parser.py
hwp_metadata_mcp/hwp_parser.py
hwp_metadata_mcp/hwpx_parser.py
hwp_metadata_mcp/models.py
hwp_metadata_mcp/server.py
hwp_metadata_mcp-1.0.0.dist-info/METADATA
hwp_metadata_mcp-1.0.0.dist-info/WHEEL
hwp_metadata_mcp-1.0.0.dist-info/entry_points.txt
hwp_metadata_mcp-1.0.0.dist-info/licenses/LICENSE
hwp_metadata_mcp-1.0.0.dist-info/RECORD
