Metadata-Version: 2.4
Name: hwp-metadata-mcp
Version: 1.0.0
Summary: MCP server for extracting metadata from Korean HWP/HWPX files
Project-URL: Homepage, https://github.com/heonseung4-del/hwp-metadata-mcp
Project-URL: Repository, https://github.com/heonseung4-del/hwp-metadata-mcp
Project-URL: Issues, https://github.com/heonseung4-del/hwp-metadata-mcp/issues
Author-email: Heonseung Lee <hs2254123@gmail.com>
License: BSD-3-Clause
License-File: LICENSE
Keywords: document,hancom,hwp,hwpx,korean,mcp,metadata
Classifier: Development Status :: 4 - Beta
Classifier: Intended Audience :: Developers
Classifier: License :: OSI Approved :: BSD License
Classifier: Programming Language :: Python :: 3
Classifier: Programming Language :: Python :: 3.10
Classifier: Programming Language :: Python :: 3.11
Classifier: Programming Language :: Python :: 3.12
Classifier: Topic :: Software Development :: Libraries :: Python Modules
Classifier: Topic :: Text Processing :: General
Requires-Python: >=3.10
Requires-Dist: mcp>=1.0.0
Requires-Dist: olefile>=0.46
Requires-Dist: pydantic>=2.0.0
Provides-Extra: dev
Requires-Dist: pytest-asyncio>=0.21.0; extra == 'dev'
Requires-Dist: pytest>=7.0.0; extra == 'dev'
